TakeStringAnalysis/__init__.py
TakeStringAnalysis/analyzer.py
string_analysis/__init__.py
string_analysis/analyzer.py
TakeStringAnalysis-0.0.2.dist-info/METADATA
TakeStringAnalysis-0.0.2.dist-info/WHEEL
TakeStringAnalysis-0.0.2.dist-info/top_level.txt
TakeStringAnalysis-0.0.2.dist-info/RECORD
