Metadata-Version: 2.1
Name: TakeStringAnalysis
Version: 0.0.2
Summary: This package returns a similar string from a stream
Home-page: UNKNOWN
Author: Renan Santos Mendes
Author-email: renans@take.net
License: UNKNOWN
Keywords: string
Platform: UNKNOWN
Classifier: Programming Language :: Python :: 3
Classifier: License :: OSI Approved :: MIT License
Classifier: Operating System :: OS Independent
Requires-Dist: pyjarowinkler (==1.8)
